Metadata-Version: 1.0
Name: EloadConsts
Version: 0.0
Summary: This module contains consts for the programm "eload" 
Home-page: UNKNOWN
Author: Igor Korobeinikov
Author-email: igorkorobigor@gmail.com
License: UNKNOWN
Platform: UNKNOWN
